dspc_bot_ctrl/__init__.py
dspc_bot_ctrl/__main__.py
dspc_bot_ctrl/bot_functions.py
dspc_bot_ctrl/dspc_bot.py
dspc_bot_ctrl/ss_stream.py
dspc_bot_ctrl/telegram_poller.py
dspc_bot_ctrl/user_identifier.py
dspc_bot_ctrl/window_manager.py
dspc_bot_ctrl-1.0.2.dist-info/LICENSE
dspc_bot_ctrl-1.0.2.dist-info/METADATA
dspc_bot_ctrl-1.0.2.dist-info/WHEEL
dspc_bot_ctrl-1.0.2.dist-info/top_level.txt
dspc_bot_ctrl-1.0.2.dist-info/RECORD
