Metadata-Version: 2.1
Name: dspc-bot-ctrl
Version: 1.0.2
Summary: Controller for bot to control your PC through telegram messages
Home-page: https://github.com/krrgeorges/dspc_bot_ctrl
Author: Rojit George
Author-email: rojitrgeorge@gmail.com
License: UNKNOWN
Platform: UNKNOWN
Classifier: Programming Language :: Python :: 3
Classifier: License :: OSI Approved :: GNU General Public License (GPL)
Classifier: Operating System :: Microsoft :: Windows :: Windows 10
Requires-Python: >=3.6
